sapui5_xml_linter.py
sapui5_xml_linter-0.0.4.dist-info/METADATA
sapui5_xml_linter-0.0.4.dist-info/WHEEL
sapui5_xml_linter-0.0.4.dist-info/entry_points.txt
sapui5_xml_linter-0.0.4.dist-info/top_level.txt
sapui5_xml_linter-0.0.4.dist-info/RECORD
