Metadata-Version: 2.1
Name: sapui5-xml-linter
Version: 0.0.4
Summary: Checks SAPUI5 XML views for unnecessary attributes and empty tags, and changes them if necessary
Author-email: Daniel Kullmann <python@danielkullmann.de>
License: MIT
Keywords: sapui5,linter
Requires-Dist: lxml
Requires-Dist: config-path
